CHANGES.md
LICENSE.md
MANIFEST.in
README.md
VERSION
setup.py
bin/iceberg
src/iceberg/__init__.py
src/iceberg.egg-info/PKG-INFO
src/iceberg.egg-info/SOURCES.txt
src/iceberg.egg-info/dependency_links.txt
src/iceberg.egg-info/namespace_packages.txt
src/iceberg.egg-info/not-zip-safe
src/iceberg.egg-info/requires.txt
src/iceberg.egg-info/top_level.txt
src/iceberg/discovery/__init__.py
src/iceberg/discovery/discovery.py
src/iceberg/discovery/image_disc.py
src/iceberg/executor/__init__.py
src/iceberg/executor/executor.py
src/iceberg/executor/penguins.py
src/iceberg/executor/rivers.py
src/iceberg/executor/seals.py
src/iceberg/iceberg_parser/__init__.py
src/iceberg/iceberg_parser/iceberg_parser.py
src/iceberg/iceberg_parser/landcover_parser.py
src/iceberg/iceberg_parser/penguins_parser.py
src/iceberg/iceberg_parser/rivers_parser.py
src/iceberg/iceberg_parser/seals_parser.py