Metadata-Version: 2.1
Name: iceberg
Version: 0.4
Summary: The ICEBERG workflow middleware
Home-page: https://www.github.com/iceberg-project/iceberg-middleware/
Author: ICEBERG Team
Author-email: iceberg-ci@googlegroups.com
License: UNKNOWN
Platform: UNKNOWN
Classifier: Development Status :: 1 - Planning
Classifier: Intended Audience :: Developers
Classifier: Environment :: Console
Classifier: Programming Language :: Python
Classifier: Programming Language :: Python :: 3
Classifier: Programming Language :: Python :: 3.6
Classifier: Topic :: Utilities
Classifier: Topic :: System :: Distributed Computing
Classifier: Topic :: Scientific/Engineering
Classifier: Operating System :: MacOS :: MacOS X
Classifier: Operating System :: POSIX
Classifier: Operating System :: Unix
